aichatchatting/__init__.py
aichatchatting/build/AIChatChattingFactory.py
aichatchatting/build/__init__.py
aichatchatting/chatprocessor/__init__.py
aichatchatting/chatprocessor/data/RequestV1.py
aichatchatting/chatprocessor/data/RequestV1Schema.py
aichatchatting/chatprocessor/data/ResponseV1.py
aichatchatting/chatprocessor/data/__init__.py
aichatchatting/chatprocessor/logic/BasicService.py
aichatchatting/chatprocessor/logic/IBasicService.py
aichatchatting/chatprocessor/logic/__init__.py
aichatchatting/cmddinterpreter/__init__.py
aichatchatting/cmddinterpreter/logic/BasicCommandSet.py
aichatchatting/cmddinterpreter/logic/BasicService.py
aichatchatting/cmddinterpreter/logic/IBasicService.py
aichatchatting/cmddinterpreter/logic/__init__.py
aichatchatting/partialfacade/__init__.py
aichatchatting/partialfacade/operations/__init__.py
aichatchatting/partialfacade/operations/version1/ChattingOperations.py
aichatchatting/partialfacade/operations/version1/TopicsOperations.py
aichatchatting/partialfacade/operations/version1/__init__.py
aichatchatting/topics/__init__.py
aichatchatting/topics/data/Topic.py
aichatchatting/topics/data/TopicSchema.py
aichatchatting/topics/data/__init__.py
aichatchatting/topics/logic/ITopicsService.py
aichatchatting/topics/logic/TopicsService.py
aichatchatting/topics/logic/__init__.py
aichatchatting/topics/persistence/ITopicsPersistence.py
aichatchatting/topics/persistence/TopicsMemoryPersistence.py
aichatchatting/topics/persistence/TopicsMongoDbPersistence.py
aichatchatting/topics/persistence/__init__.py
eic_aichat_chatting-1.0.0.dist-info/LICENSE
eic_aichat_chatting-1.0.0.dist-info/METADATA
eic_aichat_chatting-1.0.0.dist-info/WHEEL
eic_aichat_chatting-1.0.0.dist-info/top_level.txt
eic_aichat_chatting-1.0.0.dist-info/zip-safe
eic_aichat_chatting-1.0.0.dist-info/RECORD
