Metadata-Version: 2.1
Name: eic-aichat-chatting
Version: 1.0.0
Summary: AI Chat Chatting in Python
Home-page: https://bitbucket.org/entinco/eic-ai-prototypes/src/master/lib-aichatchatting-python
Author: Enterprise Innovation Consulting LLC
Author-email: seroukhov@entico.com
License: Commercial
Platform: any
Classifier: Intended Audience :: Developers
Classifier: License :: Other/Proprietary License
Classifier: Operating System :: OS Independent
Classifier: Programming Language :: Python
Classifier: Programming Language :: Python :: 3.12
Classifier: Programming Language :: Python :: 3.12
Classifier: Programming Language :: Python :: 3.12
Classifier: Programming Language :: Python :: 3.12
Classifier: Topic :: Software Development :: Libraries :: Python Modules
License-File: LICENSE
Requires-Dist: pip-services4-commons >=0.0.0
Requires-Dist: pip-services4-components >=0.0.0
Requires-Dist: pip-services4-config >=0.0.0
Requires-Dist: pip-services4-data >=0.0.0
Requires-Dist: pip-services4-http >=0.0.0
Requires-Dist: pip-services4-mongodb >=0.0.0
Requires-Dist: pip-services4-persistence >=0.0.0
Requires-Dist: pip-services4-prometheus >=0.0.0
Requires-Dist: pip-services4-rpc >=0.0.0
Requires-Dist: pip-services4-swagger >=0.0.0
